{
    "name": "Yellow Arrow Saint Paul",
    "location": "Concord Street and Grand Ave (Facing North), St. Paul, Minnesota",
    "dataDownloadLink": "https://example.com/data1",
    "purpose": "Analyzing the use of Flashing Yellow Arrows on stoplights as turn safety functions. This page contains Saint Paul information",
    "projectName": "Development of Guidelines for Permitted Left-Turn Phasing Using Flashing Yellow Arrows",
    "researchPaperLink": "https://www.cts.umn.edu/publications/report/development-of-guidelines-for-permitted-left-turn-phasing-using-flashing-yellow-arrows",
    "author": "Gary Davis, John Hourdos, Vahid Moshtagh",
    "image": "ProjectImages/SaintPaul-YellowArrow.png",
    "gps": "44.893142, -93.034320",
    "metadata": {
        "resolution": "640x480",
        "fps": "15",
        "dates": "September 2012",
        "size": "37.6 GB"
    }
}